LICENSE
MANIFEST.in
README.md
setup.py
Hmm/Hmm.c
Hmm/Hmm.pxd
Hmm/Hmm.pyx
Hmm/Hmm1.c
Hmm/Hmm1.pxd
Hmm/Hmm1.pyx
Hmm/Hmm2.c
Hmm/Hmm2.pyx
Hmm/HmmState.c
Hmm/HmmState.pxd
Hmm/HmmState.pyx
Hmm/__init__.py
NlpToolkit_Hmm_Cy.egg-info/PKG-INFO
NlpToolkit_Hmm_Cy.egg-info/SOURCES.txt
NlpToolkit_Hmm_Cy.egg-info/dependency_links.txt
NlpToolkit_Hmm_Cy.egg-info/requires.txt
NlpToolkit_Hmm_Cy.egg-info/top_level.txt
nlptoolkit_hmm_cy.egg-info/PKG-INFO
nlptoolkit_hmm_cy.egg-info/SOURCES.txt
nlptoolkit_hmm_cy.egg-info/dependency_links.txt
nlptoolkit_hmm_cy.egg-info/requires.txt
nlptoolkit_hmm_cy.egg-info/top_level.txt