Metadata-Version: 2.4
Name: nlptoolkit-hmm-cy
Version: 1.0.5
Summary: Hidden Markov Model Library
Home-page: https://github.com/StarlangSoftware/Hmm-Cy
Author: olcaytaner
Author-email: olcay.yildiz@ozyegin.edu.tr
License-File: LICENSE
Requires-Dist: NlpToolkit-Math-Cy
Requires-Dist: NlpToolkit-DataStructure-Cy
Dynamic: author
Dynamic: author-email
Dynamic: description
Dynamic: description-content-type
Dynamic: home-page
Dynamic: license-file
Dynamic: requires-dist
Dynamic: summary
